imgoptimize/__init__.py
imgoptimize/_threading.py
imgoptimize/gui.py
imgoptimize/imgoptimize.py
imgoptimize/optimize.py
img_optimize-0.1.4.dist-info/LICENSE
img_optimize-0.1.4.dist-info/METADATA
img_optimize-0.1.4.dist-info/WHEEL
img_optimize-0.1.4.dist-info/top_level.txt
img_optimize-0.1.4.dist-info/RECORD
