Metadata-Version: 2.1
Name: img-optimize
Version: 0.1.4
Summary: A python library and GUI application to optimize image files.
Home-page: https://github.com/irahorecka/img-optimize
Author: Ira Horecka
Author-email: ira89@icloud.com
License: MIT
Platform: UNKNOWN
Classifier: Development Status :: 3 - Alpha
Classifier: License :: OSI Approved :: MIT License
Classifier: Programming Language :: Python
Classifier: Programming Language :: Python :: 3.6
Classifier: Programming Language :: Python :: 3.7
Classifier: Programming Language :: Python :: 3.8
Classifier: Topic :: Software Development :: Libraries
Classifier: Topic :: Software Development :: Libraries :: Python Modules
Classifier: Intended Audience :: Developers
Requires-Python: >=3.6
Requires-Dist: PyQt5
Requires-Dist: QDarkStyle
Requires-Dist: Pillow
